mosaici/__init__.py
mosaici/__main__.py
mosaici/base_mosaic.py
mosaici/block.py
mosaici/exceptions.py
mosaici/indexpack.py
mosaici/main.py
mosaici/mosaic.py
mosaici/order.py
mosaici/pattern.py
mosaici/protocol.py
mosaici/store.py
mosaici/template.py
mosaici/app/__init__.py
mosaici/app/first_run.py
mosaici/app/mosaici_actions.py
mosaici/app/tools.py
mosaici-0.9.dist-info/METADATA
mosaici-0.9.dist-info/WHEEL
mosaici-0.9.dist-info/entry_points.txt
mosaici-0.9.dist-info/top_level.txt
mosaici-0.9.dist-info/RECORD
