Metadata-Version: 2.1
Name: mosaici
Version: 0.9
Summary: Protocol For Make Secure Data Use Template.
Home-page: https://github.com/Class-Tooraj/mosaici
Author: ToorajJahangiri
Author-email: Toorajjahangiri@gmail.com
License: MIT - License
Platform: UNKNOWN
Classifier: Programming Language :: Python :: 3
Classifier: Programming Language :: Python :: 3.10
Classifier: Topic :: Software Development :: Libraries :: Python Modules
Requires-Python: >=3.10.*
Requires-Dist: colorama
